spa_data_structures/__init__.py
spa_data_structures/pyCRed.py
spa_data_structures/pyJPListe.py
spa_data_structures/pyJPRed.py
spa_data_structures/pyJPStek.py
spa_data_structures/pyNizListe.py
spa_data_structures/pyNizStek.py
spa_data_structures-0.0.1.dist-info/LICENSE.txt
spa_data_structures-0.0.1.dist-info/METADATA
spa_data_structures-0.0.1.dist-info/WHEEL
spa_data_structures-0.0.1.dist-info/top_level.txt
spa_data_structures-0.0.1.dist-info/RECORD
