Metadata-Version: 2.1
Name: spa_data_structures
Version: 0.0.1
Summary: Simple SPA Package
Author: PTF
Author-email: elmin.marevac2019@size.ba
License-File: LICENSE.txt
